[
  {
    "title": "test",
    "description": "test",
    "priority": "emergency",
    "department": "Security",
    "user": "Current User",
    "status": "closed",
    "teamId": "TEAM-DEFAULT",
    "id": "T-1006",
    "createdAt": "2026-06-17T06:49:44.120Z",
    "comments": [
      {
        "user": "anthonycyber",
        "text": "this ticket has been resolved.",
        "isInternal": false,
        "id": "C-1781679006851",
        "timestamp": "2026-06-17T06:50:06.851Z"
      }
    ],
    "isEscalated": false,
    "assignedTo": "anthonycyber",
    "modifier": "anthonycyber"
  },
  {
    "title": "TOO LONG FOR TICKETS",
    "description": "Close all Tickets",
    "priority": "emergency",
    "department": "Security",
    "user": "Current User",
    "status": "closed",
    "teamId": "TEAM-DEFAULT",
    "id": "T-1005",
    "createdAt": "2026-06-12T16:17:53.834Z",
    "comments": [],
    "isEscalated": false,
    "modifier": "anthonycyber",
    "assignedTo": "anthonycyber"
  },
  {
    "title": "test",
    "description": "test ticket",
    "priority": "emergency",
    "department": "Security",
    "user": "Current User",
    "status": "closed",
    "teamId": "TEAM-DEFAULT",
    "id": "T-1004",
    "createdAt": "2026-06-06T15:48:47.298Z",
    "comments": [],
    "isEscalated": false,
    "modifier": "anthonycyber"
  },
  {
    "id": "T-1001",
    "teamId": "TEAM-DEFAULT",
    "title": "SYSTEM LATENCY IN NEURAL CORE",
    "description": "The neural core is experiencing significant lag during high-load processing cycles.",
    "priority": "high",
    "status": "closed",
    "isEscalated": false,
    "user": "Alpha-01",
    "department": "Infrastructure",
    "createdAt": "2026-06-06T12:44:29.434Z",
    "comments": [
      {
        "id": "C-1",
        "user": "System",
        "text": "Auto-detected latency spike.",
        "timestamp": "2026-06-06T12:44:29.434Z"
      }
    ],
    "modifier": "anthonycyber"
  },
  {
    "id": "T-1002",
    "teamId": "TEAM-DEFAULT",
    "title": "UI GLITCH IN BENTO GRID",
    "description": "Bento boxes are not aligning correctly on mobile viewports.",
    "priority": "normal",
    "status": "closed",
    "isEscalated": true,
    "user": "Beta-02",
    "department": "IT",
    "createdAt": "2026-06-06T09:44:29.434Z",
    "comments": [
      {
        "user": "anthonycyber",
        "text": "jlkfjsdsd",
        "isInternal": false,
        "id": "C-1781281430564",
        "timestamp": "2026-06-12T16:23:50.564Z"
      }
    ],
    "modifier": "anthonycyber"
  },
  {
    "id": "T-1003",
    "teamId": "TEAM-DEFAULT",
    "title": "CRITICAL SECURITY BREACH ATTEMPT",
    "description": "Detected unauthorized access attempt from external node 192.168.1.50.",
    "priority": "emergency",
    "status": "closed",
    "isEscalated": true,
    "user": "Sentinel-X",
    "department": "Security",
    "createdAt": "2026-06-06T14:14:29.434Z",
    "comments": [
      {
        "user": "anthonycyber",
        "text": "THIS TICKET IS AN EMERGENCY, IT HAS BEEN ESCALATED TO THE SECURITY TEAM.",
        "isInternal": false,
        "id": "C-1780759287248",
        "timestamp": "2026-06-06T15:21:27.248Z"
      }
    ],
    "modifier": "anthonycyber",
    "assignedTo": "anthonycyber",
    "tasks": [
      {
        "id": "TSK-1780759323478",
        "description": "Complete reconnaissance of the breach attempt.",
        "isComplete": true,
        "createdAt": "2026-06-06T15:22:03.478Z"
      }
    ]
  }
]
